chartfactor/__init__.py
chartfactor/main.py
chartfactor/pytransform/__init__.py
chartfactor/pytransform/platforms/darwin/aarch64/_pytransform.dylib
chartfactor/pytransform/platforms/darwin/x86_64/_pytransform.dylib
chartfactor/pytransform/platforms/ios/aarch64/_pytransform.dylib
chartfactor/pytransform/platforms/linux/aarch32/_pytransform.so
chartfactor/pytransform/platforms/linux/aarch64/_pytransform.so
chartfactor/pytransform/platforms/linux/armv6/_pytransform.so
chartfactor/pytransform/platforms/linux/armv7/_pytransform.so
chartfactor/pytransform/platforms/linux/x86/_pytransform.so
chartfactor/pytransform/platforms/linux/x86_64/_pytransform.so
chartfactor/pytransform/platforms/musl/x86_64/_pytransform.so
chartfactor/pytransform/platforms/windows/x86/_pytransform.dll
chartfactor/pytransform/platforms/windows/x86_64/_pytransform.dll
chartfactor/src/__init__.py
chartfactor/src/attribute.py
chartfactor/src/build_info.py
chartfactor/src/cf.py
chartfactor/src/code_generator.py
chartfactor/src/color.py
chartfactor/src/column.py
chartfactor/src/compare_metric.py
chartfactor/src/field.py
chartfactor/src/filter.py
chartfactor/src/grid.py
chartfactor/src/legend.py
chartfactor/src/markline.py
chartfactor/src/metric.py
chartfactor/src/provider.py
chartfactor/src/row.py
chartfactor/src/assets/__init__.py
chartfactor/src/assets/css/__init__.py
chartfactor/src/assets/css/style.css
chartfactor/src/assets/js/__init__.py
chartfactor/src/assets/js/cf-message-event-listener.js
chartfactor/src/assets/js/execute-python.js
chartfactor/src/assets/js/jupyter-notebook-active-cell-change.js
chartfactor/src/assets/js/kaggle-specs.js
chartfactor/src/assets/js/send-message.js
chartfactor/src/resources/__init__.py
chartfactor/src/resources/commons.py
chartfactor/src/resources/constants.py
chartfactor/src/resources/html_template.py
chartfactor/src/resources/static_files_manager.py
chartfactor-5.1.28.dist-info/LICENSE
chartfactor-5.1.28.dist-info/METADATA
chartfactor-5.1.28.dist-info/WHEEL
chartfactor-5.1.28.dist-info/top_level.txt
chartfactor-5.1.28.dist-info/RECORD
