Metadata-Version: 2.2
Name: chartfactor
Version: 5.1.28
Summary: Integrates ChartFactor with Jupyter Notebooks
Home-page: https://github.com/Aktiun/chartfactor-py
Author: Aktiun
Author-email: juan.dominguez@aktiun.com
Keywords: aktiun,jupyter,jupyterhub,jupyterlab,chartfactor-py
Classifier: Programming Language :: Python :: 3
Classifier: Operating System :: OS Independent
Requires-Python: >=3.7
License-File: LICENSE
Requires-Dist: numpy>=1.19.5
Requires-Dist: pandas
Requires-Dist: pandasql>=0.7.3
Requires-Dist: pygeohash==1.2.0
Requires-Dist: jsonschema>=3.2.0
Requires-Dist: colorama>=0.4.4
Requires-Dist: importlib-resources>=5.4.0
Requires-Dist: tzlocal~=4.1
Requires-Dist: chartfactor-jlab-ext==5.1.28
Dynamic: author
Dynamic: author-email
Dynamic: classifier
Dynamic: description
Dynamic: description-content-type
Dynamic: home-page
Dynamic: keywords
Dynamic: requires-dist
Dynamic: requires-python
Dynamic: summary
